README.md
setup.py
salvus_mesher_lite/RELEASE-VERSION
salvus_mesher_lite/__init__.py
salvus_mesher_lite/attenuation.py
salvus_mesher_lite/cm.py
salvus_mesher_lite/compat.py
salvus_mesher_lite/connectivity.py
salvus_mesher_lite/elements.py
salvus_mesher_lite/global_numbering.py
salvus_mesher_lite/helpers.py
salvus_mesher_lite/models_1D.py
salvus_mesher_lite/skeleton.py
salvus_mesher_lite/structured_grid_2D.py
salvus_mesher_lite/unstructured_mesh.py
salvus_mesher_lite/version.py
salvus_mesher_lite.egg-info/PKG-INFO
salvus_mesher_lite.egg-info/SOURCES.txt
salvus_mesher_lite.egg-info/dependency_links.txt
salvus_mesher_lite.egg-info/requires.txt
salvus_mesher_lite.egg-info/top_level.txt
salvus_mesher_lite/data/Moon_Weber2011.bm
salvus_mesher_lite/data/VPREMOON.bm
salvus_mesher_lite/data/VPREMOON_noLVL.bm
salvus_mesher_lite/data/ak135.bm
salvus_mesher_lite/data/ak135f.bm
salvus_mesher_lite/data/iasp91.bm
salvus_mesher_lite/data/mars_sohl.bm
salvus_mesher_lite/data/prem_ani.bm
salvus_mesher_lite/data/prem_ani_ocean.bm
salvus_mesher_lite/data/prem_ani_one_crust.bm
salvus_mesher_lite/data/prem_crust20_cont.bm
salvus_mesher_lite/data/prem_crust20_global.bm
salvus_mesher_lite/data/prem_crust20_ocean.bm
salvus_mesher_lite/data/prem_iso.bm
salvus_mesher_lite/data/prem_iso_one_crust.bm
salvus_mesher_lite/interface/__init__.py
salvus_mesher_lite/interface/__main__.py
salvus_mesher_lite/interface/validate.py
salvus_mesher_lite/interface/schemas/salvus_mesher_lite_0.0.1.json
salvus_mesher_lite/mesh/__init__.py
salvus_mesher_lite/mesh/cartesian.py
salvus_mesher_lite/mesh/common.py
salvus_mesher_lite/mesh/run_mesher.py
salvus_mesher_lite/mesh/spherical.py
salvus_mesher_lite/src/angle.c
salvus_mesher_lite/src/centroid.c
salvus_mesher_lite/src/connectivity.c
salvus_mesher_lite/src/facets.c
salvus_mesher_lite/src/hmin_max.c
salvus_mesher_lite/src/sort.c
salvus_mesher_lite/tests/__init__.py
salvus_mesher_lite/tests/__main__.py
salvus_mesher_lite/tests/test_attenuation.py
salvus_mesher_lite/tests/test_global_numbering.py
salvus_mesher_lite/tests/test_interface.py
salvus_mesher_lite/tests/test_models_1D.py
salvus_mesher_lite/tests/test_skeleton.py
